ImageHash-4.3.1.data/data/images/imagehash.png
ImageHash-4.3.1.data/scripts/find_similar_images.py
imagehash/__init__.py
imagehash/py.typed
ImageHash-4.3.1.dist-info/LICENSE
ImageHash-4.3.1.dist-info/METADATA
ImageHash-4.3.1.dist-info/WHEEL
ImageHash-4.3.1.dist-info/top_level.txt
ImageHash-4.3.1.dist-info/RECORD
