Metadata-Version: 2.1
Name: ImageHash
Version: 4.3.1
Summary: Image Hashing library
Home-page: https://github.com/JohannesBuchner/imagehash
Author: Johannes Buchner
Author-email: buchner.johannes@gmx.at
License: 2-clause BSD License
Platform: UNKNOWN
License-File: LICENSE
